{
	"name": "Onprem-bronze-data-ingest",
	"properties": {
		"activities": [
			{
				"name": "ConfigTable",
				"type": "Lookup",
				"dependsOn": [],
				"policy": {
					"timeout": "0.12:00:00",
					"retry": 0,
					"retryIntervalInSeconds": 30,
					"secureOutput": false,
					"secureInput": false
				},
				"userProperties": [],
				"typeProperties": {
					"source": {
						"type": "AzureSqlSource",
						"sqlReaderQuery": "SELECT  * FROM [dbo].[ConfigTable]",
						"queryTimeout": "02:00:00",
						"partitionOption": "None"
					},
					"dataset": {
						"referenceName": "ds_azuresql_conftbl",
						"type": "DatasetReference"
					},
					"firstRowOnly": false
				}
			},
			{
				"name": "ForEach Tables",
				"type": "ForEach",
				"dependsOn": [
					{
						"activity": "ConfigTable",
						"dependencyConditions": [
							"Succeeded"
						]
					}
				],
				"userProperties": [],
				"typeProperties": {
					"items": {
						"value": "@activity('ConfigTable').output.value",
						"type": "Expression"
					},
					"activities": [
						{
							"name": "sqlserverTOadls",
							"type": "Copy",
							"dependsOn": [],
							"policy": {
								"timeout": "0.12:00:00",
								"retry": 0,
								"retryIntervalInSeconds": 30,
								"secureOutput": false,
								"secureInput": false
							},
							"userProperties": [],
							"typeProperties": {
								"source": {
									"type": "SqlServerSource",
									"sqlReaderQuery": {
										"value": "SELECT * FROM \n[test_retaildb].[dbo].@{item().TableName}\nWHERE @{item().WatermarkColumn} > '@{item().LastModifiedDate}'",
										"type": "Expression"
									},
									"queryTimeout": "02:00:00",
									"partitionOption": "None"
								},
								"sink": {
									"type": "ParquetSink",
									"storeSettings": {
										"type": "AzureBlobFSWriteSettings"
									},
									"formatSettings": {
										"type": "ParquetWriteSettings"
									}
								},
								"enableStaging": false,
								"translator": {
									"type": "TabularTranslator",
									"typeConversion": true,
									"typeConversionSettings": {
										"allowDataTruncation": true,
										"treatBooleanAsNumber": false
									}
								}
							},
							"inputs": [
								{
									"referenceName": "SqlServerTable1",
									"type": "DatasetReference"
								}
							],
							"outputs": [
								{
									"referenceName": "ds_bronze_adls",
									"type": "DatasetReference",
									"parameters": {
										"p_container": {
											"value": "@item().SinkContainer",
											"type": "Expression"
										},
										"p_folder": {
											"value": "@item().FolderName",
											"type": "Expression"
										}
									}
								}
							]
						},
						{
							"name": "Update_lastmodified_date",
							"type": "Lookup",
							"dependsOn": [
								{
									"activity": "sqlserverTOadls",
									"dependencyConditions": [
										"Succeeded"
									]
								}
							],
							"policy": {
								"timeout": "0.12:00:00",
								"retry": 0,
								"retryIntervalInSeconds": 30,
								"secureOutput": false,
								"secureInput": false
							},
							"userProperties": [],
							"typeProperties": {
								"source": {
									"type": "SqlServerSource",
									"sqlReaderQuery": {
										"value": "SELECT max(@{item().WatermarkColumn}) AS last_date\nFROM [test_retaildb].[dbo].@{item().TableName}",
										"type": "Expression"
									},
									"queryTimeout": "02:00:00",
									"partitionOption": "None"
								},
								"dataset": {
									"referenceName": "ds_lastmod_up",
									"type": "DatasetReference"
								}
							}
						},
						{
							"name": "Stored procedure lastmodifieddate",
							"type": "SqlServerStoredProcedure",
							"dependsOn": [
								{
									"activity": "Update_lastmodified_date",
									"dependencyConditions": [
										"Succeeded"
									]
								}
							],
							"policy": {
								"timeout": "0.12:00:00",
								"retry": 0,
								"retryIntervalInSeconds": 30,
								"secureOutput": false,
								"secureInput": false
							},
							"userProperties": [],
							"typeProperties": {
								"storedProcedureName": "[dbo].[UpdateConfigWatermark]",
								"storedProcedureParameters": {
									"LastModifiedDate": {
										"value": {
											"value": "@activity('Update_lastmodified_date').output.firstRow.last_date",
											"type": "Expression"
										},
										"type": "DateTime"
									},
									"TableName": {
										"value": {
											"value": "@item().TableName",
											"type": "Expression"
										},
										"type": "String"
									}
								}
							},
							"linkedServiceName": {
								"referenceName": "ls_azuresqldb",
								"type": "LinkedServiceReference"
							}
						}
					]
				}
			}
		],
		"annotations": []
	}
}